dstools/__init__.py
dstools/casa.py
dstools/cli/askap_preprocess.py
dstools/cli/atca_cal.py
dstools/cli/create_model.py
dstools/cli/extract_ds.py
dstools/cli/insert_model.py
dstools/cli/plot_ds.py
dstools/cli/selfcal.py
dstools/cli/subtract_model.py
dstools/dynamic_spectrum.py
dstools/imaging.py
dstools/logger.py
dstools/mask.py
dstools/ms.py
dstools/plotting.py
dstools/utils.py
dstools/viewer.py
radio_dstools-2.0.0.dist-info/LICENSE.txt
radio_dstools-2.0.0.dist-info/METADATA
radio_dstools-2.0.0.dist-info/WHEEL
radio_dstools-2.0.0.dist-info/entry_points.txt
radio_dstools-2.0.0.dist-info/RECORD
