Metadata-Version: 2.3
Name: radio-dstools
Version: 2.0.0
Summary: A processing pipeline to produce dynamic spectra from visibilities.
Author: Joshua Pritchard
Author-email: joshua.pritchard@csiro.au
Requires-Python: >=3.11,<3.12
Classifier: License :: OSI Approved :: MIT License
Classifier: Programming Language :: Python :: 3
Classifier: Programming Language :: Python :: 3.11
Requires-Dist: astropy (==6.1.7)
Requires-Dist: cal-cabb (>=0.1.0,<0.2.0)
Requires-Dist: casatasks (>=6.7,<7.0)
Requires-Dist: click (>=8.0.3,<9.0.0)
Requires-Dist: colorlog (>=6.8.2,<7.0.0)
Requires-Dist: dask (>=2024.11.2,<2025.0.0)
Requires-Dist: fixms (>=0.4.0,<0.5.0)
Requires-Dist: h5py (>=3.11.0,<4.0.0)
Requires-Dist: matplotlib (>=3.8.2,<4.0.0)
Requires-Dist: mpl-point-clicker (>=0.4.1,<0.5.0)
Requires-Dist: numpy (>=2.0.0,<3.0.0)
Requires-Dist: pandas (==2.2.3)
Requires-Dist: python-casacore (>=3.6.1,<4.0.0)
Requires-Dist: radio-beam (>=0.3.8,<0.4.0)
Requires-Dist: rm-lite (>=2025.4.0,<2026.0.0)
Requires-Dist: scipy (>=1.14.1,<2.0.0)
Requires-Dist: xarray (>=2024.11.0,<2025.0.0)
